{
        "dates": [
            {
                "images": "http://img1.ali213.net/glpic/2018/09/20/584_20180920120033974.jpg",
                "title": "《太吾绘卷》配置要求高吗？配置要求介绍",
                "url": "http://3g.ali213.net/gl/html/267541.html",
                "desc": "　　游戏将于9月21日上架，是一款以神话和武侠为题材的独立游戏。今天小编为各位武侠迷们带来的就是太吾绘卷配置要求介绍，感兴趣的玩家不要错过！"
            },
            {
                "images": "http://img1.ali213.net/glpic/2018/09/22/584_2018092230933249.png",
                "title": "《太吾绘卷》新手图文攻略 新手怎么玩？",
                "url": "http://3g.ali213.net/gl/html/268011.html",
                "desc": "　　很多玩家都是第一时间入手了太吾绘卷，不过由于没玩过这种类型的游戏，大多数人进入游戏后不知道该干嘛。所以今天小编便为大家准备了“tedshan”分享的太吾绘卷新手图文攻略，还不会玩的小伙伴赶紧来看看吧。"
            },
            {
                "images": "http://img1.ali213.net/glpic/2018/09/21/584_2018092120339831.jpg",
                "title": "《太吾绘卷》有哪些出生地？出生地信息一览",
                "url": "http://3g.ali213.net/gl/html/267859.html",
                "desc": "　　太吾绘卷游戏中人物的出生地决定了很多人物的属性，下面小编来分享一下太吾绘卷出生地的信息，希望能够给大家提供一点参考。"
            },
            {
                "images": "http://img1.ali213.net/glpic/2018/09/29/584_2018092911113300.png",
                "title": "《太吾绘卷》出生时节如何选择？24节气属性汇总",
                "url": "http://3g.ali213.net/gl/html/267897.html",
                "desc": "　　太吾绘卷出生在不同的节气会带来不同的buff属性效果，具体是怎样的呢？相信不少玩家都不清楚，下面小编就为大家带来太吾绘卷出生24节气属性汇总，一起来看看吧。"
            },
            {
                "images": "http://img1.ali213.net/glpic/2018/09/28/584_2018092832706216.png",
                "title": "《太吾绘卷》机略怎么使用？机略技能介绍",
                "url": "http://3g.ali213.net/gl/html/269241.html",
                "desc": "　　太吾绘卷机略怎么使用？很多新手玩家战斗的时候发现自己的机略点一直是零，不知道怎么用，所以今天小编给大家带来的就是太吾绘卷机略技能介绍，需要的朋友不妨进来看看哦。"
            },
            {
                "images": "http://img1.ali213.net/glpic/2018/09/28/584_2018092811171052.png",
                "title": "《太吾绘卷》开局武学选择 开局武学有哪些可以选择？",
                "url": "http://3g.ali213.net/gl/html/269087.html",
                "desc": "　　太吾绘卷开局武学有哪些可以选择？想必大家都不是特别清楚吧，所以今天小编给大家带来的就是太吾绘卷开局武学选择，需要的朋友不妨进来看看哦。"
            }
        ],
        "count": 8
}